{
  "copilot_action_name": "WINDOWS-ENSURE-FIREWALL-ENABLED-COPILOT-ACTION",
  "description": "Ensures Windows Defender Firewall is enabled and correctly configured across Domain, Private, and Public profiles. Verifies service state, enables profiles when disabled, turns on logging for allowed and blocked connections, and sets a default log path if missing. Emits NDJSON with a verification record, a summary, and per-profile details.",
  "technology": "Windows",
  "icon": "windows",
  "repo_url": "https://raw.githubusercontent.com/socfortress/WINDOWS-ENSURE-FIREWALL-ENABLED-COPILOT-ACTION/refs/heads/main/Ensure-Firewall-Enabled.ps1",
  "script_name": "Ensure-Firewall-Enabled.ps1",
  "version": "1.0.0",
  "last_updated": "2025-09-09T00:00:00Z"
}
